taskerapi/__init__.py
taskerapi/const.py
taskerapi/exceptions.py
taskerapi/helpers.py
taskerapi/tasks.py
taskerapi/typing.py
taskerapi/data/Backup.tsk.xml
taskerapi/data/Device_Info.tsk.xml
taskerapi/data/Get_Voice.tsk.xml
taskerapi/data/Run_Code.tsk.xml
taskerapi-0.0.3.dist-info/LICENSE
taskerapi-0.0.3.dist-info/METADATA
taskerapi-0.0.3.dist-info/WHEEL
taskerapi-0.0.3.dist-info/top_level.txt
taskerapi-0.0.3.dist-info/RECORD
