Metadata-Version: 2.1
Name: taskerapi
Version: 0.0.3
Summary: Library to control Tasker Android app
Home-page: https://github.com/lone-faerie/taskerapi
Download-URL: https://github.com/lone-faerie/taskerapi
Author: Lone Faerie
Author-email: lone.faerie@gmail.com
License: GPLv3
Classifier: Programming Language :: Python :: 3
Classifier: License :: OSI Approved :: GNU General Public License v3 (GPLv3)
Classifier: Operating System :: OS Independent
Requires-Python: >=3.9
License-File: LICENSE
